[{"line":2,"elements":[{"start_timestamp":"2022-02-15T09:21:30.304Z","before":[{"result":{"duration":3000800,"status":"passed"},"match":{"location":"stepdefinitions.Hooks.setUp()"}}],"line":6,"name":"TC05_parametre kullanimi   # parametre icin aranacak yer tirnak icine alinir","description":"","id":"us1003-parametre-ile-stepdefinitions-olusturma;tc05-parametre-kullanimi---#-parametre-icin-aranacak-yer-tirnak-icine-alinir","after":[{"result":{"duration":6319003100,"status":"passed"},"match":{"location":"stepdefinitions.Hooks.tearDown(io.cucumber.java.Scenario)"}}],"type":"scenario","keyword":"Scenario","steps":[{"result":{"duration":19256331200,"status":"passed"},"line":8,"name":"kullanici amazon sayfasina gider","match":{"location":"stepdefinitions.AmazonStepDefinitions.kullanici_amazon_sayfasina_gider()"},"keyword":"Given "},{"result":{"duration":7249002000,"status":"passed"},"line":9,"name":"\"iPhone\" icin arama yapar","match":{"arguments":[{"val":"\"iPhone\"","offset":0}],"location":"stepdefinitions.AmazonStepDefinitions.icin_arama_yapar(java.lang.String)"},"keyword":"And "},{"result":{"duration":331999600,"status":"passed"},"line":10,"name":"sonuclarin \"iPhone\" icerdigini test eder","match":{"arguments":[{"val":"\"iPhone\"","offset":11}],"location":"stepdefinitions.AmazonStepDefinitions.sonuclarin_icerdigini_test_eder(java.lang.String)"},"keyword":"Then "},{"result":{"status":"undefined"},"line":11,"name":"ana sayfayi kapatir","match":{},"keyword":"And "}],"tags":[{"name":"@parametreliTest"},{"name":"@paralel1"}]}],"name":"US1003 parametre ile stepdefinitions olusturma","description":"","id":"us1003-parametre-ile-stepdefinitions-olusturma","keyword":"Feature","uri":"file:src/test/resources/features/US1003_ParametreKullanimi.feature","tags":[{"name":"@parametreliTest","type":"Tag","location":{"line":1,"column":1}}]}]